{
  "titre": "Hugo es tu là?",
  "auteur": "Victor Hugo",
  "troupe": "TIM La Parade",
  "image": "data/img/Hugoestul.jpg",
  "photographe": "",
  "description": "Cabaret littéraire masqué semi-improvisé vous embarque dans le carnaval hugolien, plongeant dans l’imaginaire collectif, explorant l’œuvre de Gavroche à Léopoldine, de Ruy Blas à Quasimodo, de Guernesey aux grands discours politiques. Ce soir, le metteur en scène et sa troupe auditionne publiquement toute une mascarade de personnages grotesques et sublimes qui interprètent, chantent, déclament, à chaque numéro un florilège de poèmes, discours, extraits de pièces et de romans. Pour le final, c’est aux spectateurs-jury que revient le choix du personnage qui portera le masque de Victor lui- même…"
}
